Metadata-Version: 2.1
Name: rhasspy-wake-porcupine-hermes
Version: 0.3.0
Summary: UNKNOWN
Home-page: https://github.com/rhasspy/rhasspy-wake-porcupine-hermes
Author: Michael Hansen
Author-email: mike@rhasspy.org
License: UNKNOWN
Platform: UNKNOWN
Classifier: Programming Language :: Python :: 3
Classifier: Programming Language :: Python :: 3.7
Classifier: Programming Language :: Python :: 3.8
Classifier: License :: OSI Approved :: MIT License
Requires-Python: >=3.7
